{
    "status": "success",
    "data": {
        "sectionEntitiesMap": {
            "505f664d-2831-5e7f-8781-ec33d13ae25d": {
                "721bed7d-b8d6-5702-bade-c8cf6b5df22e": {
                    "description": "Соус вершковий, сир моцарело, куряче філе, бекон, помідори. Розмір на вибір.",
                    "imageUrl": "https://d1ralsognjng37.cloudfront.net/0a436ff3-69e0-474c-98fa-3d7a1a09bb55.jpeg",
                    "price": 14299,
                    "title": "Чікен",
                    "uuid": "721bed7d-b8d6-5702-bade-c8cf6b5df22e",
                    "nutritionalInfo": {
                        "allergens": [
                            ""
                        ],
                        "displayString": ""
                    },
                    "suspendReason": null,
                    "suspendUntil": 0,
                    "classifications": []
                },
                "1b2341b4-10d7-58e1-bb3d-454d9faafc0e": {
                    "description": "Соус із томатів Пелаті, сир моцарела, бекон, салямі, печериці, корнішони. ",
                    "imageUrl": "https://d1ralsognjng37.cloudfront.net/194e6353-f939-4527-a035-9abe02619fab.jpeg",
                    "price": 18999,
                    "title": "1+1 Кантрі 30 см",
                    "uuid": "1b2341b4-10d7-58e1-bb3d-454d9faafc0e",
                    "nutritionalInfo": {
                        "allergens": [
                            ""
                        ],
                        "displayString": ""
                    },
                    "suspendReason": null,
                    "suspendUntil": 0,
                    "classifications": []
                },
                "49e65991-e779-5105-88ce-cbb0891fff4a": {
                    "description": "290г",
                    "imageUrl": "https://d1ralsognjng37.cloudfront.net/73bac6d8-4a6d-4746-8dea-682f2518336f.jpeg",
                    "price": 6199,
                    "title": "Кальцоне з моцарелою та вершковим соусом",
                    "uuid": "49e65991-e779-5105-88ce-cbb0891fff4a",
                    "nutritionalInfo": {
                        "allergens": [
                            ""
                        ],
                        "displayString": ""
                    },
                    "suspendReason": null,
                    "suspendUntil": 0,
                    "classifications": []
                },
                "0e2e7036-ebc5-57d9-838f-d7ffac75fc5d": {
                    "description": "",
                    "imageUrl": "",
                    "price": 2400,
                    "title": "Pepsi",
                    "uuid": "0e2e7036-ebc5-57d9-838f-d7ffac75fc5d",
                    "nutritionalInfo": {
                        "allergens": [
                            ""
                        ],
                        "displayString": ""
                    },
                    "suspendReason": null,
                    "suspendUntil": 0,
                    "classifications": []
                },
                "eb6efa0c-c7a4-4db7-9c22-a0d89a4d55e5": {
                    "description": "Піца ЛаВіта (30см), піца Мафія (30см), піца Суперсалямі (30см), напій Pepsi (1000мл/2шт). ",
                    "imageUrl": "https://d1ralsognjng37.cloudfront.net/c05fb31e-c7a0-4ff2-bc7c-ed2b02e64b73.jpeg",
                    "price": 44399,
                    "title": "Комбо 3",
                    "uuid": "eb6efa0c-c7a4-4db7-9c22-a0d89a4d55e5",
                    "nutritionalInfo": {
                        "allergens": [
                            ""
                        ],
                        "displayString": ""
                    },
                    "suspendReason": null,
                    "suspendUntil": 0,
                    "classifications": []
                },
                "1c12f97f-dd3c-50b3-be78-62ca4ed224db": {
                    "description": "500мл",
                    "imageUrl": "",
                    "price": 4400,
                    "title": "Карлсберг",
                    "uuid": "1c12f97f-dd3c-50b3-be78-62ca4ed224db",
                    "nutritionalInfo": {
                        "allergens": [
                            ""
                        ],
                        "displayString": ""
                    },
                    "suspendReason": null,
                    "suspendUntil": 0,
                    "classifications": []
                },
                "14d21ee9-8a2a-43f1-af1f-c37879321b3f": {
                    "description": "Піца Кантрі нова (30см), піца Імперія (30см), піца Гриль Делюкс (30см), піца Премьер (30см), піца Чікен (30см).",
                    "imageUrl": "https://d1ralsognjng37.cloudfront.net/a1898074-46ae-40a2-9136-721b39b43256.jpeg",
                    "price": 55500,
                    "title": "Комбо \"Щаслива п'ятірка\"",
                    "uuid": "14d21ee9-8a2a-43f1-af1f-c37879321b3f",
                    "nutritionalInfo": {
                        "allergens": [
                            ""
                        ],
                        "displayString": ""
                    },
                    "suspendReason": null,
                    "suspendUntil": 0,
                    "classifications": []
                },
                "23f93660-a827-5cdb-ae8d-0a3941408293": {
                    "description": "Соус із томатів Пелаті, сир моцарела, салямі, соус Чилі. Розмір на вибір.",
                    "imageUrl": "https://d1ralsognjng37.cloudfront.net/c20d209b-b5e4-42b0-ae41-54600554611f.jpeg",
                    "price": 12799,
                    "title": "Діабло",
                    "uuid": "23f93660-a827-5cdb-ae8d-0a3941408293",
                    "nutritionalInfo": {
                        "allergens": [
                            ""
                        ],
                        "displayString": ""
                    },
                    "suspendReason": null,
                    "suspendUntil": 0,
                    "endorsement": {
                        "text": "Гостра страва",
                        "iconUrl": "https://uber-test.s3.amazonaws.com/badge_check@3x.png"
                    },
                    "classifications": []
                },
                "ff6ed875-fbde-5dcb-a71b-23a105170bd3": {
                    "description": "Соус із томатів Пелаті, сир моцарела, шинка, салямі, бекон, баварські ковбаски, куряче філе. Розмір на вибір.",
                    "imageUrl": "https://d1ralsognjng37.cloudfront.net/46a8530a-0225-457f-8125-9b4c9bbf11a8.jpeg",
                    "price": 15299,
                    "title": "Супер м'ясна",
                    "uuid": "ff6ed875-fbde-5dcb-a71b-23a105170bd3",
                    "nutritionalInfo": {
                        "allergens": [
                            ""
                        ],
                        "displayString": ""
                    },
                    "suspendReason": null,
                    "suspendUntil": 0,
                    "classifications": []
                },
                "66809476-76e8-4489-8f98-fe637d24117a": {
                    "description": "Піца Баварска (30см), піца 4 сири (30см), кальцоне з моцарелою, кальцоне з шинкою і салямі, кальцоне з беконом и ковбасками.",
                    "imageUrl": "https://d1ralsognjng37.cloudfront.net/da18071b-ba62-4723-bcb4-da76b56e029b.jpeg",
                    "price": 45900,
                    "title": "Комбо \"Три кальцоне в подарунок\"",
                    "uuid": "66809476-76e8-4489-8f98-fe637d24117a",
                    "nutritionalInfo": {
                        "allergens": [
                            ""
                        ],
                        "displayString": ""
                    },
                    "suspendReason": null,
                    "suspendUntil": 0,
                    "classifications": []
                },
                "39d7849d-580e-5742-8ddb-1eda022707b3": {
                    "description": "Соус із томатів Пелаті, сир моцарела, куряче філе, ананас. Розмір на вибір.",
                    "imageUrl": "https://d1ralsognjng37.cloudfront.net/88d5db48-4bba-42fc-b329-6894a1438de0.jpeg",
                    "price": 7999,
                    "title": "Гаваї",
                    "uuid": "39d7849d-580e-5742-8ddb-1eda022707b3",
                    "nutritionalInfo": {
                        "allergens": [
                            ""
                        ],
                        "displayString": ""
                    },
                    "suspendReason": null,
                    "suspendUntil": 0,
                    "classifications": []
                },
                "425fb2a0-d310-5fd7-aba1-9bc36538e382": {
                    "description": "Соус із томатів Пелаті, сир моцарела, салямі, шинка, куряче філе, ананас. Розмір на вибір.",
                    "imageUrl": "https://d1ralsognjng37.cloudfront.net/7159fdf0-e4fb-4495-b306-cf42b2c76ab7.jpeg",
                    "price": 14999,
                    "title": "Тропікана",
                    "uuid": "425fb2a0-d310-5fd7-aba1-9bc36538e382",
                    "nutritionalInfo": {
                        "allergens": [
                            ""
                        ],
                        "displayString": ""
                    },
                    "suspendReason": null,
                    "suspendUntil": 0,
                    "classifications": []
                },
                "e6dfff3c-c18e-5a4e-b6aa-fd8880bf5911": {
                    "description": "",
                    "imageUrl": "https://d1ralsognjng37.cloudfront.net/36b90410-0fe9-4a7c-ad0a-3c347f0e2876.jpeg",
                    "price": 9499,
                    "title": "Курячі нагетси",
                    "uuid": "e6dfff3c-c18e-5a4e-b6aa-fd8880bf5911",
                    "nutritionalInfo": {
                        "allergens": [
                            ""
                        ],
                        "displayString": ""
                    },
                    "suspendReason": null,
                    "suspendUntil": 0,
                    "classifications": []
                },
                "0a5e30cc-1fbe-5de9-b042-9018b7379032": {
                    "description": "Соус із томатів Пелаті, сир моцарела, бекон, печериці, куряче філе, цибуля. Розмір на вибір.",
                    "imageUrl": "https://d1ralsognjng37.cloudfront.net/0d91e5cf-5c9e-4392-b03f-8a0cda097ba9.jpeg",
                    "price": 10499,
                    "title": "Барбекю",
                    "uuid": "0a5e30cc-1fbe-5de9-b042-9018b7379032",
                    "nutritionalInfo": {
                        "allergens": [
                            ""
                        ],
                        "displayString": ""
                    },
                    "suspendReason": null,
                    "suspendUntil": 0,
                    "classifications": []
                },
                "5f85d6ea-b841-58e6-8aa7-81907f2fda24": {
                    "description": "",
                    "imageUrl": "",
                    "price": 2400,
                    "title": "Pepsi Black",
                    "uuid": "5f85d6ea-b841-58e6-8aa7-81907f2fda24",
                    "nutritionalInfo": {
                        "allergens": [
                            ""
                        ],
                        "displayString": ""
                    },
                    "suspendReason": null,
                    "suspendUntil": 0,
                    "classifications": []
                },
                "92649e85-8806-57ea-a2e2-2b8ae600bd18": {
                    "description": "",
                    "imageUrl": "",
                    "price": 2200,
                    "title": "Вода аквамінерале",
                    "uuid": "92649e85-8806-57ea-a2e2-2b8ae600bd18",
                    "nutritionalInfo": {
                        "allergens": [
                            ""
                        ],
                        "displayString": ""
                    },
                    "suspendReason": null,
                    "suspendUntil": 8640000000,
                    "classifications": []
                },
                "034c515a-4d31-5067-ae35-f9fd33990e20": {
                    "description": "1000мл",
                    "imageUrl": "",
                    "price": 6800,
                    "title": "Львівське 1715",
                    "uuid": "034c515a-4d31-5067-ae35-f9fd33990e20",
                    "nutritionalInfo": {
                        "allergens": [
                            ""
                        ],
                        "displayString": ""
                    },
                    "suspendReason": null,
                    "suspendUntil": 0,
                    "classifications": []
                },
                "b63fbb41-fa1d-4f3b-82ee-afe5bf3644c4": {
                    "description": "Соус із томатів Пелаті, сир моцарела, баварські ковбаски, шинка, куряче філе, помідори. ",
                    "imageUrl": "https://d1ralsognjng37.cloudfront.net/1a3b086e-fd11-4335-9526-34df0bedb6ae.jpeg",
                    "price": 22599,
                    "title": "1+1 Баварська 30 см",
                    "uuid": "b63fbb41-fa1d-4f3b-82ee-afe5bf3644c4",
                    "nutritionalInfo": {
                        "allergens": [
                            ""
                        ],
                        "displayString": ""
                    },
                    "suspendReason": null,
                    "suspendUntil": 0,
                    "classifications": []
                },
                "6d56fdec-6892-52b8-9b38-e90a450e249c": {
                    "description": "1000мл",
                    "imageUrl": "",
                    "price": 9800,
                    "title": "Кроненбург бланк 1664",
                    "uuid": "6d56fdec-6892-52b8-9b38-e90a450e249c",
                    "nutritionalInfo": {
                        "allergens": [
                            ""
                        ],
                        "displayString": ""
                    },
                    "suspendReason": null,
                    "suspendUntil": 0,
                    "classifications": []
                },
                "3f682fbb-f3dd-5576-b122-df714855726a": {
                    "description": "Соус із томатів Пелаті, сир моцарела, шинка, баварські ковбаски, печериці, корнішони, цибуля. Розмір на вибір.",
                    "imageUrl": "https://d1ralsognjng37.cloudfront.net/de386840-ba01-453e-bf50-03cc92cc89c2.jpeg",
                    "price": 10499,
                    "title": "Імперія",
                    "uuid": "3f682fbb-f3dd-5576-b122-df714855726a",
                    "nutritionalInfo": {
                        "allergens": [
                            ""
                        ],
                        "displayString": ""
                    },
                    "suspendReason": null,
                    "suspendUntil": 0,
                    "classifications": []
                },
                "aa1fc60a-2fcf-5021-98f3-bf60827d4032": {
                    "description": "Соус із томатів Пелаті, сир моцарела, бекон, шинка, баварські ковбаски, салямі, сир Пармезан. Розмір на вибір.",
                    "imageUrl": "https://d1ralsognjng37.cloudfront.net/b02d16e7-8c63-4a97-8f32-abfa7eadd24e.jpeg",
                    "price": 15299,
                    "title": "Коза ностра",
                    "uuid": "aa1fc60a-2fcf-5021-98f3-bf60827d4032",
                    "nutritionalInfo": {
                        "allergens": [
                            ""
                        ],
                        "displayString": ""
                    },
                    "suspendReason": null,
                    "suspendUntil": 0,
                    "classifications": []
                },
                "052ae66d-c5a3-5514-b869-46542d5d1cd5": {
                    "description": "Соус із томатів Пелаті, соус Чилі, сир моцарела, салямі, баварські ковбаски, печериці, перець салатний, сир Пармезан. Розмір на вибір.",
                    "imageUrl": "https://d1ralsognjng37.cloudfront.net/c3131e5e-a60a-4190-9c34-7457166bbcd0.jpeg",
                    "price": 14999,
                    "title": "Гриль Де Люкс",
                    "uuid": "052ae66d-c5a3-5514-b869-46542d5d1cd5",
                    "nutritionalInfo": {
                        "allergens": [
                            ""
                        ],
                        "displayString": ""
                    },
                    "suspendReason": null,
                    "suspendUntil": 0,
                    "endorsement": {
                        "text": "Гостра страва",
                        "iconUrl": "https://uber-test.s3.amazonaws.com/badge_check@3x.png"
                    },
                    "classifications": []
                },
                "f805c403-c2c3-56cd-a6d3-3d4bdd6063ba": {
                    "description": "",
                    "imageUrl": "",
                    "price": 600,
                    "title": "Соус з гірчицею",
                    "uuid": "f805c403-c2c3-56cd-a6d3-3d4bdd6063ba",
                    "nutritionalInfo": {
                        "allergens": [
                            ""
                        ],
                        "displayString": ""
                    },
                    "suspendReason": null,
                    "suspendUntil": 0,
                    "classifications": []
                },
                "6eaeb2d9-1585-518d-9dc8-e284d70790fb": {
                    "description": "",
                    "imageUrl": "",
                    "price": 600,
                    "title": "Майонез",
                    "uuid": "6eaeb2d9-1585-518d-9dc8-e284d70790fb",
                    "nutritionalInfo": {
                        "allergens": [
                            ""
                        ],
                        "displayString": ""
                    },
                    "suspendReason": null,
                    "suspendUntil": 0,
                    "classifications": []
                },
                "d8dc4ad7-e628-5e5b-a477-fdc4e1bfd11d": {
                    "description": "Соус із томатів Пелаті, салямі, бекон, куряче філе, печериці, оливки. Розмір на вибір.",
                    "imageUrl": "https://d1ralsognjng37.cloudfront.net/2113a163-f4e9-4e91-ac43-5fcfd3894572.jpeg",
                    "price": 12799,
                    "title": "Ла Віта",
                    "uuid": "d8dc4ad7-e628-5e5b-a477-fdc4e1bfd11d",
                    "nutritionalInfo": {
                        "allergens": [
                            ""
                        ],
                        "displayString": ""
                    },
                    "suspendReason": null,
                    "suspendUntil": 0,
                    "classifications": []
                },
                "0924d1e7-7cae-5e3d-9957-f9a7b30d4921": {
                    "description": "500мл",
                    "imageUrl": "",
                    "price": 3900,
                    "title": "Львівське 1715",
                    "uuid": "0924d1e7-7cae-5e3d-9957-f9a7b30d4921",
                    "nutritionalInfo": {
                        "allergens": [
                            ""
                        ],
                        "displayString": ""
                    },
                    "suspendReason": null,
                    "suspendUntil": 0,
                    "classifications": []
                },
                "133f4fe9-9bd7-53c1-829e-4e0f55b1606e": {
                    "description": "Соус із томатів Пелаті, сир моцарела, шинка, бекон, куряче філе, перець салатний, цибуля. Розмір на вибір.",
                    "imageUrl": "https://d1ralsognjng37.cloudfront.net/e3a5a9c4-8595-4704-99ef-3035e8e36dbb.jpeg",
                    "price": 10499,
                    "title": "Прем'єр",
                    "uuid": "133f4fe9-9bd7-53c1-829e-4e0f55b1606e",
                    "nutritionalInfo": {
                        "allergens": [
                            ""
                        ],
                        "displayString": ""
                    },
                    "suspendReason": null,
                    "suspendUntil": 0,
                    "classifications": []
                },
                "e6a63454-30c5-47b3-a056-c488886259f7": {
                    "description": "Піца Тропікана нова (30см), піца Кантрі нова (30см).",
                    "imageUrl": "https://d1ralsognjng37.cloudfront.net/2791c191-005c-4702-9847-f1813d530f2e.jpeg",
                    "price": 19900,
                    "title": "Комбо 4 ",
                    "uuid": "e6a63454-30c5-47b3-a056-c488886259f7",
                    "nutritionalInfo": {
                        "allergens": [
                            ""
                        ],
                        "displayString": ""
                    },
                    "suspendReason": null,
                    "suspendUntil": 0,
                    "classifications": []
                },
                "71cbfbe5-f836-4922-bf30-fb30dad1cf69": {
                    "description": "Піца Дьябло нова (30см), піца Американа (30см).",
                    "imageUrl": "https://d1ralsognjng37.cloudfront.net/91283d4b-5625-413a-a351-54d26c44fce0.jpeg",
                    "price": 23900,
                    "title": "Комбо 5",
                    "uuid": "71cbfbe5-f836-4922-bf30-fb30dad1cf69",
                    "nutritionalInfo": {
                        "allergens": [
                            ""
                        ],
                        "displayString": ""
                    },
                    "suspendReason": null,
                    "suspendUntil": 0,
                    "classifications": []
                },
                "71558b32-f713-5d75-9295-6eb25462335a": {
                    "description": "Соус вершковий, сир моцарела, куряче філе, сир Рокфор, сир Брі, печериці. Розмір на вибір.",
                    "imageUrl": "https://d1ralsognjng37.cloudfront.net/172e1dd9-d7d2-41f7-aa1b-5b8894e054c9.jpeg",
                    "price": 14999,
                    "title": "Верона",
                    "uuid": "71558b32-f713-5d75-9295-6eb25462335a",
                    "nutritionalInfo": {
                        "allergens": [
                            ""
                        ],
                        "displayString": ""
                    },
                    "suspendReason": null,
                    "suspendUntil": 0,
                    "classifications": []
                },
                "809b40b6-c2d8-5dad-9c0c-954d433479e5": {
                    "description": "",
                    "imageUrl": "",
                    "price": 2400,
                    "title": "Mirinda",
                    "uuid": "809b40b6-c2d8-5dad-9c0c-954d433479e5",
                    "nutritionalInfo": {
                        "allergens": [
                            ""
                        ],
                        "displayString": ""
                    },
                    "suspendReason": null,
                    "suspendUntil": 0,
                    "classifications": []
                },
                "e220ac32-ab73-5fc5-bc00-3d824d8fdf71": {
                    "description": "Соус із томатів Пелаті, сир моцарела, шинка, куряче філе, печериці, помідори. Розмір на вибір.",
                    "imageUrl": "https://d1ralsognjng37.cloudfront.net/3e3ed3b3-ecfa-4ddc-9f15-95e0dde8c525.jpeg",
                    "price": 14999,
                    "title": "Pizza King",
                    "uuid": "e220ac32-ab73-5fc5-bc00-3d824d8fdf71",
                    "nutritionalInfo": {
                        "allergens": [
                            ""
                        ],
                        "displayString": ""
                    },
                    "suspendReason": null,
                    "suspendUntil": 0,
                    "classifications": []
                },
                "7c74cc31-9b96-5013-ae15-277a5a89abc0": {
                    "description": "Соус із томатів Пелаті, сир моцарела, помідори. Розмір на вибір.",
                    "imageUrl": "https://d1ralsognjng37.cloudfront.net/819a78a0-3a90-46a7-a007-eb134f67d6e4.jpeg",
                    "price": 7999,
                    "title": "Маргарита",
                    "uuid": "7c74cc31-9b96-5013-ae15-277a5a89abc0",
                    "nutritionalInfo": {
                        "allergens": [
                            ""
                        ],
                        "displayString": ""
                    },
                    "suspendReason": null,
                    "suspendUntil": 0,
                    "classifications": []
                },
                "4f2251c2-2d2e-5654-b5f7-396780c1f42c": {
                    "description": "Соус вершковий, сир моцарела, сир Рокфор, сир Брі, сир Пармезан. Розмір на вибір.",
                    "imageUrl": "https://d1ralsognjng37.cloudfront.net/51a02bf5-5671-46d4-80a0-ab43e4ad5e02.jpeg",
                    "price": 15299,
                    "title": "Чотири сира",
                    "uuid": "4f2251c2-2d2e-5654-b5f7-396780c1f42c",
                    "nutritionalInfo": {
                        "allergens": [
                            ""
                        ],
                        "displayString": ""
                    },
                    "suspendReason": null,
                    "suspendUntil": 0,
                    "classifications": []
                },
                "5dcfa6a1-eeb8-5958-88be-df82692026fd": {
                    "description": "1000мл",
                    "imageUrl": "",
                    "price": 3900,
                    "title": "7UP",
                    "uuid": "5dcfa6a1-eeb8-5958-88be-df82692026fd",
                    "nutritionalInfo": {
                        "allergens": [
                            ""
                        ],
                        "displayString": ""
                    },
                    "suspendReason": null,
                    "suspendUntil": 8640000000,
                    "classifications": []
                },
                "12d6a811-7777-5cc9-be5c-d84f79a227fe": {
                    "description": "",
                    "imageUrl": "https://d1ralsognjng37.cloudfront.net/aa45644c-c7e3-4302-ae73-836a18d8ea68.jpeg",
                    "price": 5299,
                    "title": "Дольки картопляне",
                    "uuid": "12d6a811-7777-5cc9-be5c-d84f79a227fe",
                    "nutritionalInfo": {
                        "allergens": [
                            ""
                        ],
                        "displayString": ""
                    },
                    "suspendReason": null,
                    "suspendUntil": 0,
                    "classifications": []
                },
                "5a29149b-1445-42b8-8fef-ad24664218ff": {
                    "description": "Піца Піца Кінг (36см/2шт), піца Супер Салямі (22см/3шт).",
                    "imageUrl": "https://d1ralsognjng37.cloudfront.net/132dda87-704f-4927-af25-4c3b7a0c5ee5.jpeg",
                    "price": 49598,
                    "title": "Комбо \"Для великих та маленьких\"",
                    "uuid": "5a29149b-1445-42b8-8fef-ad24664218ff",
                    "nutritionalInfo": {
                        "allergens": [
                            ""
                        ],
                        "displayString": ""
                    },
                    "suspendReason": null,
                    "suspendUntil": 0,
                    "classifications": []
                },
                "55600d02-9822-5d01-95d9-eb6496ef1fcf": {
                    "description": "",
                    "imageUrl": "",
                    "price": 600,
                    "title": "Соус BBQ",
                    "uuid": "55600d02-9822-5d01-95d9-eb6496ef1fcf",
                    "nutritionalInfo": {
                        "allergens": [
                            ""
                        ],
                        "displayString": ""
                    },
                    "suspendReason": null,
                    "suspendUntil": 0,
                    "classifications": []
                },
                "903d966c-03df-514c-954a-390b3a774af6": {
                    "description": "Соус із томатів Пелаті, сир моцарела, помідори, печериці, перець салатний, оливки, цибуля. Розмір на вибір.",
                    "imageUrl": "https://d1ralsognjng37.cloudfront.net/e4c5f829-d660-4277-ae4f-d02318fa34b8.jpeg",
                    "price": 7999,
                    "title": "Овочева",
                    "uuid": "903d966c-03df-514c-954a-390b3a774af6",
                    "nutritionalInfo": {
                        "allergens": [
                            ""
                        ],
                        "displayString": ""
                    },
                    "suspendReason": null,
                    "suspendUntil": 0,
                    "classifications": []
                },
                "c092d65a-94e1-50c6-9b83-88ebc3925db1": {
                    "description": "270г.",
                    "imageUrl": "https://d1ralsognjng37.cloudfront.net/1ab027a7-6dab-40c2-8447-0af3f9464c0e.jpeg",
                    "price": 5999,
                    "title": "Шоколадний десерт",
                    "uuid": "c092d65a-94e1-50c6-9b83-88ebc3925db1",
                    "nutritionalInfo": {
                        "allergens": [
                            ""
                        ],
                        "displayString": ""
                    },
                    "suspendReason": null,
                    "suspendUntil": 0,
                    "classifications": []
                },
                "1b7b09e1-6d12-5e7c-95b3-f8de50ee7000": {
                    "description": "З вершковим соусом.",
                    "imageUrl": "https://d1ralsognjng37.cloudfront.net/5ba4199b-ea51-4a68-80fd-a8e262287c91.jpeg",
                    "price": 7599,
                    "title": "Кальцоне з моцарелою, беконом та мисливськими ковбасками",
                    "uuid": "1b7b09e1-6d12-5e7c-95b3-f8de50ee7000",
                    "nutritionalInfo": {
                        "allergens": [
                            ""
                        ],
                        "displayString": ""
                    },
                    "suspendReason": null,
                    "suspendUntil": 0,
                    "classifications": []
                },
                "26f16f40-60b2-4e16-a930-a5dacb20bbd9": {
                    "description": "Соус із томатів Пелаті, сир моцарела, куряче філе, ананас. ",
                    "imageUrl": "https://d1ralsognjng37.cloudfront.net/88d5db48-4bba-42fc-b329-6894a1438de0.jpeg",
                    "price": 16599,
                    "title": "1+1 Гаваї 30 см",
                    "uuid": "26f16f40-60b2-4e16-a930-a5dacb20bbd9",
                    "nutritionalInfo": {
                        "allergens": [
                            ""
                        ],
                        "displayString": ""
                    },
                    "suspendReason": null,
                    "suspendUntil": 0,
                    "classifications": []
                },
                "ea9c4d2b-9846-5c48-aca3-3641e2f11d36": {
                    "description": "Соус із томатів Пелаті, сир моцарела, салямі, сир Рокфор. Розмір на вибір.",
                    "imageUrl": "https://d1ralsognjng37.cloudfront.net/3893f067-986f-40b4-a9e5-30c40c9c42cc.jpeg",
                    "price": 10499,
                    "title": "Салямі чіз",
                    "uuid": "ea9c4d2b-9846-5c48-aca3-3641e2f11d36",
                    "nutritionalInfo": {
                        "allergens": [
                            ""
                        ],
                        "displayString": ""
                    },
                    "suspendReason": null,
                    "suspendUntil": 0,
                    "classifications": []
                },
                "daf1b591-2b0d-51e7-927b-d19c8d09701a": {
                    "description": "Соус із томатів Пелаті, сир моцарела, баварські ковбаски, шинка, куряче філе, помідори. Розмір на вибір.",
                    "imageUrl": "https://d1ralsognjng37.cloudfront.net/1a3b086e-fd11-4335-9526-34df0bedb6ae.jpeg",
                    "price": 15299,
                    "title": "Баварська",
                    "uuid": "daf1b591-2b0d-51e7-927b-d19c8d09701a",
                    "nutritionalInfo": {
                        "allergens": [
                            ""
                        ],
                        "displayString": ""
                    },
                    "suspendReason": null,
                    "suspendUntil": 0,
                    "classifications": []
                },
                "490b72d0-88c1-5aa6-a1fb-c9ff431289bf": {
                    "description": "",
                    "imageUrl": "",
                    "price": 600,
                    "title": "Соус карі",
                    "uuid": "490b72d0-88c1-5aa6-a1fb-c9ff431289bf",
                    "nutritionalInfo": {
                        "allergens": [
                            ""
                        ],
                        "displayString": ""
                    },
                    "suspendReason": null,
                    "suspendUntil": 0,
                    "classifications": []
                },
                "574c63ae-647c-56ad-88a6-1b22816c665f": {
                    "description": "Соус із томатів Пелаті, сир моцарела, салямі, печериці, оливки, перець салатний. Розмір на вибір.",
                    "imageUrl": "https://d1ralsognjng37.cloudfront.net/250e5bb7-b6bc-4e61-a7fa-a9fe4d89d760.jpeg",
                    "price": 10499,
                    "title": "Неаполь",
                    "uuid": "574c63ae-647c-56ad-88a6-1b22816c665f",
                    "nutritionalInfo": {
                        "allergens": [
                            ""
                        ],
                        "displayString": ""
                    },
                    "suspendReason": null,
                    "suspendUntil": 0,
                    "classifications": []
                },
                "d20f300c-a03d-5f53-8cda-ca8941f00d38": {
                    "description": "Соус вершковий, сир моцарела, шинка, салямі, сир Рокфор, сир Брі, помідори. Розмір на вибір.",
                    "imageUrl": "https://d1ralsognjng37.cloudfront.net/111837ef-fd46-4be3-ab2c-d32c70b083a8.jpeg",
                    "price": 14299,
                    "title": "Мафія",
                    "uuid": "d20f300c-a03d-5f53-8cda-ca8941f00d38",
                    "nutritionalInfo": {
                        "allergens": [
                            ""
                        ],
                        "displayString": ""
                    },
                    "suspendReason": null,
                    "suspendUntil": 0,
                    "classifications": []
                },
                "b1d53a1f-724a-4b1c-a3bc-0ae2f77c4ac6": {
                    "description": "Піца Суперсалямі (30см), піца PizzaKing (30см), напій Pepsi (1000мл).",
                    "imageUrl": "https://d1ralsognjng37.cloudfront.net/a3d51ab8-1add-4922-ad4a-ad7fb08429f1.jpeg",
                    "price": 27299,
                    "title": "Комбо 1",
                    "uuid": "b1d53a1f-724a-4b1c-a3bc-0ae2f77c4ac6",
                    "nutritionalInfo": {
                        "allergens": [
                            ""
                        ],
                        "displayString": ""
                    },
                    "suspendReason": null,
                    "suspendUntil": 0,
                    "classifications": []
                },
                "df076550-c236-57be-8bc1-517725505460": {
                    "description": "",
                    "imageUrl": "",
                    "price": 600,
                    "title": "Кетчуп",
                    "uuid": "df076550-c236-57be-8bc1-517725505460",
                    "nutritionalInfo": {
                        "allergens": [
                            ""
                        ],
                        "displayString": ""
                    },
                    "suspendReason": null,
                    "suspendUntil": 0,
                    "classifications": []
                },
                "663475ce-ad30-513c-9e62-cf741c37b2c2": {
                    "description": "1000мл",
                    "imageUrl": "",
                    "price": 7800,
                    "title": "Львівське Dunkel",
                    "uuid": "663475ce-ad30-513c-9e62-cf741c37b2c2",
                    "nutritionalInfo": {
                        "allergens": [
                            ""
                        ],
                        "displayString": ""
                    },
                    "suspendReason": null,
                    "suspendUntil": 8640000000,
                    "classifications": []
                },
                "db964cf8-7f36-55f9-adef-8a9f85bf1671": {
                    "description": "Соус вершковий, сир моцарела, бекон, шинка, салямі. Розмір на вибір.",
                    "imageUrl": "https://d1ralsognjng37.cloudfront.net/7fadce25-e3fe-4570-9f9a-ef9513d6f883.jpeg",
                    "price": 14299,
                    "title": "Американа",
                    "uuid": "db964cf8-7f36-55f9-adef-8a9f85bf1671",
                    "nutritionalInfo": {
                        "allergens": [
                            ""
                        ],
                        "displayString": ""
                    },
                    "suspendReason": null,
                    "suspendUntil": 0,
                    "classifications": []
                },
                "43758040-38ce-50ec-af1b-069e6fe5be5a": {
                    "description": "500мл",
                    "imageUrl": "",
                    "price": 3900,
                    "title": "Балтика б/а",
                    "uuid": "43758040-38ce-50ec-af1b-069e6fe5be5a",
                    "nutritionalInfo": {
                        "allergens": [
                            ""
                        ],
                        "displayString": ""
                    },
                    "suspendReason": null,
                    "suspendUntil": 0,
                    "classifications": []
                },
                "11d5e454-f25d-4fc3-a529-f4e582f19599": {
                    "description": "Піца Баварска (30см), піца Американа (30см), рулет шоколадний (3шт).",
                    "imageUrl": "https://d1ralsognjng37.cloudfront.net/dcefd269-dc31-473b-be97-1759528adf4a.jpeg",
                    "price": 42400,
                    "title": "Комбо \"Для солодкого життя\"",
                    "uuid": "11d5e454-f25d-4fc3-a529-f4e582f19599",
                    "nutritionalInfo": {
                        "allergens": [
                            ""
                        ],
                        "displayString": ""
                    },
                    "suspendReason": null,
                    "suspendUntil": 0,
                    "classifications": []
                },
                "aa55afc0-dd93-4d33-a916-14afad0b001b": {
                    "description": "Піца Супер Салямі (22см), піца Піца Кінг (22см), кальцоне з моцарелою, кальцоне з беконом и ковбасками, стріпси курячі (275г).",
                    "imageUrl": "https://d1ralsognjng37.cloudfront.net/bbfa64df-ff89-428a-8091-c74115c418ce.jpeg",
                    "price": 34900,
                    "title": "Комбо \"Піци маленькі - подарунки великі\"",
                    "uuid": "aa55afc0-dd93-4d33-a916-14afad0b001b",
                    "nutritionalInfo": {
                        "allergens": [
                            ""
                        ],
                        "displayString": ""
                    },
                    "suspendReason": null,
                    "suspendUntil": 0,
                    "classifications": []
                },
                "661e1523-a39d-557d-ad98-82f8d157da47": {
                    "description": "Соус із томатів Пелаті, сир моцарела, салямі. Розмір на вибір.",
                    "imageUrl": "https://d1ralsognjng37.cloudfront.net/54528ba8-4131-47b1-b422-fe9a0e0a8b84.jpeg",
                    "price": 12799,
                    "title": "Супер салямі",
                    "uuid": "661e1523-a39d-557d-ad98-82f8d157da47",
                    "nutritionalInfo": {
                        "allergens": [
                            ""
                        ],
                        "displayString": ""
                    },
                    "suspendReason": null,
                    "suspendUntil": 0,
                    "classifications": []
                },
                "e158eb07-3e9a-4350-8313-b4a1ac9927fd": {
                    "description": "Піца 4 сири (30см), піца Баварска (30см).",
                    "imageUrl": "https://d1ralsognjng37.cloudfront.net/09f3d326-9596-4c98-9f91-7a2a07a5c1db.jpeg",
                    "price": 27900,
                    "title": "Комбо 6",
                    "uuid": "e158eb07-3e9a-4350-8313-b4a1ac9927fd",
                    "nutritionalInfo": {
                        "allergens": [
                            ""
                        ],
                        "displayString": ""
                    },
                    "suspendReason": null,
                    "suspendUntil": 0,
                    "classifications": []
                },
                "fcc69e16-5350-4cb2-acdf-a1f832b12807": {
                    "description": "Піца Салямі Чіз (30см), піца Американа (30см), пиво Львівське (500мл/2шт). ",
                    "imageUrl": "https://d1ralsognjng37.cloudfront.net/ae566aa2-a589-4792-9dc6-aa757f76a962.jpeg",
                    "price": 28299,
                    "title": "Комбо 2",
                    "uuid": "fcc69e16-5350-4cb2-acdf-a1f832b12807",
                    "nutritionalInfo": {
                        "allergens": [
                            ""
                        ],
                        "displayString": ""
                    },
                    "suspendReason": null,
                    "suspendUntil": 0,
                    "classifications": []
                },
                "c46b63f3-7201-5cf9-b30f-dc19a2963410": {
                    "description": "З вершковим соусом.",
                    "imageUrl": "https://d1ralsognjng37.cloudfront.net/f39a0062-30f8-4d7f-8eb6-83a5aa411f13.jpeg",
                    "price": 7599,
                    "title": "Кальцоне з моцарелою, шинкою та салямі",
                    "uuid": "c46b63f3-7201-5cf9-b30f-dc19a2963410",
                    "nutritionalInfo": {
                        "allergens": [
                            ""
                        ],
                        "displayString": ""
                    },
                    "suspendReason": null,
                    "suspendUntil": 0,
                    "classifications": []
                }
            }
        },
        "sections": [
            {
                "subsectionUuids": [
                    "1e4231a5-9d58-4535-8d93-5f6f3e72a2cf",
                    "00d83446-124f-519e-a067-8cc0b81d76cf",
                    "ba97a616-799e-51ad-808e-d38507e13796",
                    "2e40fc2b-0ac8-5d96-acfe-702f0a0fe750",
                    "6cda11b8-fe6a-491b-bec4-97fefa800f06",
                    "e9e80d79-f1fb-5da0-b331-b06f5aceb974",
                    "100bca4f-7787-55ff-8d44-ec47994ea994",
                    "8b915da3-b541-5675-9a1a-a933088dd330",
                    "6cd2bb2b-3aa4-5f47-9380-e5aec54cb0cc",
                    "7caa8b78-5873-566c-b5f5-767f7e1fa2d6",
                    "5566ff5a-f961-5f93-83f5-7356e87b2b56",
                    "ac7beec0-d6aa-5294-b775-3d0e0b5d3573"
                ],
                "title": "SWITCH LANGUAGE (UKR)",
                "subtitle": "10:00 AM – 9:30 PM",
                "uuid": "505f664d-2831-5e7f-8781-ec33d13ae25d",
                "isTop": true,
                "isOnSale": true
            }
        ],
        "subsectionsMap": {
            "00d83446-124f-519e-a067-8cc0b81d76cf": {
                "itemUuids": [
                    "7c74cc31-9b96-5013-ae15-277a5a89abc0",
                    "39d7849d-580e-5742-8ddb-1eda022707b3",
                    "903d966c-03df-514c-954a-390b3a774af6",
                    "0a5e30cc-1fbe-5de9-b042-9018b7379032",
                    "3f682fbb-f3dd-5576-b122-df714855726a",
                    "ea9c4d2b-9846-5c48-aca3-3641e2f11d36",
                    "574c63ae-647c-56ad-88a6-1b22816c665f",
                    "133f4fe9-9bd7-53c1-829e-4e0f55b1606e"
                ],
                "subtitle": "",
                "title": "Королівська ціна",
                "uuid": "00d83446-124f-519e-a067-8cc0b81d76cf",
                "displayType": null
            },
            "8b915da3-b541-5675-9a1a-a933088dd330": {
                "itemUuids": [
                    "ff6ed875-fbde-5dcb-a71b-23a105170bd3",
                    "4f2251c2-2d2e-5654-b5f7-396780c1f42c",
                    "aa1fc60a-2fcf-5021-98f3-bf60827d4032",
                    "daf1b591-2b0d-51e7-927b-d19c8d09701a"
                ],
                "subtitle": "",
                "title": "Королівський вибір",
                "uuid": "8b915da3-b541-5675-9a1a-a933088dd330",
                "displayType": null
            },
            "e9e80d79-f1fb-5da0-b331-b06f5aceb974": {
                "itemUuids": [
                    "c46b63f3-7201-5cf9-b30f-dc19a2963410",
                    "49e65991-e779-5105-88ce-cbb0891fff4a",
                    "1b7b09e1-6d12-5e7c-95b3-f8de50ee7000"
                ],
                "subtitle": "",
                "title": "Кальцоне",
                "uuid": "e9e80d79-f1fb-5da0-b331-b06f5aceb974",
                "displayType": null
            },
            "100bca4f-7787-55ff-8d44-ec47994ea994": {
                "itemUuids": [
                    "71558b32-f713-5d75-9295-6eb25462335a",
                    "425fb2a0-d310-5fd7-aba1-9bc36538e382",
                    "e220ac32-ab73-5fc5-bc00-3d824d8fdf71",
                    "052ae66d-c5a3-5514-b869-46542d5d1cd5"
                ],
                "subtitle": "",
                "title": "Королівськи легенди",
                "uuid": "100bca4f-7787-55ff-8d44-ec47994ea994",
                "displayType": null
            },
            "1e4231a5-9d58-4535-8d93-5f6f3e72a2cf": {
                "itemUuids": [
                    "b63fbb41-fa1d-4f3b-82ee-afe5bf3644c4",
                    "1b2341b4-10d7-58e1-bb3d-454d9faafc0e",
                    "26f16f40-60b2-4e16-a930-a5dacb20bbd9"
                ],
                "subtitle": null,
                "title": "2 ЗА ЦІНОЮ 1",
                "uuid": "1e4231a5-9d58-4535-8d93-5f6f3e72a2cf",
                "displayType": null
            },
            "5566ff5a-f961-5f93-83f5-7356e87b2b56": {
                "itemUuids": [
                    "c092d65a-94e1-50c6-9b83-88ebc3925db1"
                ],
                "subtitle": "",
                "title": "Десерт",
                "uuid": "5566ff5a-f961-5f93-83f5-7356e87b2b56",
                "displayType": null
            },
            "2e40fc2b-0ac8-5d96-acfe-702f0a0fe750": {
                "itemUuids": [
                    "d20f300c-a03d-5f53-8cda-ca8941f00d38",
                    "db964cf8-7f36-55f9-adef-8a9f85bf1671",
                    "721bed7d-b8d6-5702-bade-c8cf6b5df22e"
                ],
                "subtitle": "",
                "title": "Королівськи фаворити",
                "uuid": "2e40fc2b-0ac8-5d96-acfe-702f0a0fe750",
                "displayType": null
            },
            "ac7beec0-d6aa-5294-b775-3d0e0b5d3573": {
                "itemUuids": [
                    "43758040-38ce-50ec-af1b-069e6fe5be5a",
                    "1c12f97f-dd3c-50b3-be78-62ca4ed224db",
                    "0924d1e7-7cae-5e3d-9957-f9a7b30d4921",
                    "6d56fdec-6892-52b8-9b38-e90a450e249c",
                    "034c515a-4d31-5067-ae35-f9fd33990e20",
                    "663475ce-ad30-513c-9e62-cf741c37b2c2",
                    "0e2e7036-ebc5-57d9-838f-d7ffac75fc5d",
                    "5f85d6ea-b841-58e6-8aa7-81907f2fda24",
                    "809b40b6-c2d8-5dad-9c0c-954d433479e5",
                    "5dcfa6a1-eeb8-5958-88be-df82692026fd",
                    "92649e85-8806-57ea-a2e2-2b8ae600bd18"
                ],
                "subtitle": "",
                "title": "Напої",
                "uuid": "ac7beec0-d6aa-5294-b775-3d0e0b5d3573",
                "displayType": null
            },
            "6cda11b8-fe6a-491b-bec4-97fefa800f06": {
                "itemUuids": [
                    "b1d53a1f-724a-4b1c-a3bc-0ae2f77c4ac6",
                    "fcc69e16-5350-4cb2-acdf-a1f832b12807",
                    "eb6efa0c-c7a4-4db7-9c22-a0d89a4d55e5",
                    "e6a63454-30c5-47b3-a056-c488886259f7",
                    "71cbfbe5-f836-4922-bf30-fb30dad1cf69",
                    "e158eb07-3e9a-4350-8313-b4a1ac9927fd",
                    "14d21ee9-8a2a-43f1-af1f-c37879321b3f",
                    "66809476-76e8-4489-8f98-fe637d24117a",
                    "aa55afc0-dd93-4d33-a916-14afad0b001b",
                    "11d5e454-f25d-4fc3-a529-f4e582f19599",
                    "5a29149b-1445-42b8-8fef-ad24664218ff"
                ],
                "subtitle": "",
                "title": "Комбо набір",
                "uuid": "6cda11b8-fe6a-491b-bec4-97fefa800f06",
                "displayType": null
            },
            "ba97a616-799e-51ad-808e-d38507e13796": {
                "itemUuids": [
                    "661e1523-a39d-557d-ad98-82f8d157da47",
                    "23f93660-a827-5cdb-ae8d-0a3941408293",
                    "d8dc4ad7-e628-5e5b-a477-fdc4e1bfd11d"
                ],
                "subtitle": "",
                "title": "Королівська класика",
                "uuid": "ba97a616-799e-51ad-808e-d38507e13796",
                "displayType": null
            },
            "7caa8b78-5873-566c-b5f5-767f7e1fa2d6": {
                "itemUuids": [
                    "6eaeb2d9-1585-518d-9dc8-e284d70790fb",
                    "df076550-c236-57be-8bc1-517725505460",
                    "490b72d0-88c1-5aa6-a1fb-c9ff431289bf",
                    "f805c403-c2c3-56cd-a6d3-3d4bdd6063ba",
                    "55600d02-9822-5d01-95d9-eb6496ef1fcf"
                ],
                "subtitle": "",
                "title": "Соуси",
                "uuid": "7caa8b78-5873-566c-b5f5-767f7e1fa2d6",
                "displayType": null
            },
            "6cd2bb2b-3aa4-5f47-9380-e5aec54cb0cc": {
                "itemUuids": [
                    "12d6a811-7777-5cc9-be5c-d84f79a227fe",
                    "e6dfff3c-c18e-5a4e-b6aa-fd8880bf5911"
                ],
                "subtitle": "",
                "title": "Закуски",
                "uuid": "6cd2bb2b-3aa4-5f47-9380-e5aec54cb0cc",
                "displayType": null
            }
        },
        "title": "Pizza King (просп. Перемоги)",
        "uuid": "512bb454-af2b-487c-ae12-899545193419",
        "categories": [
            "₴₴",
            "Піца",
            "Італійська",
            "Європейська"
        ],
        "cuisineList": [
            "Піца",
            "Італійська",
            "Європейська"
        ],
        "priceBucket": "₴₴",
        "etaRange": {
            "text": "40–50 min",
            "iconUrl": ""
        },
        "ratingBadge": {
            "text": "<span><span style=\"font-family: inherit; color: #3a3a48;\">4.1 <img src=\"https://d1a3f4spazzrp4.cloudfront.net/static/images/Star_Black_Eats_3.png\" width=\"14\" height=\"14\" vertical-align=\"middle\"> </span><span style=\"font-family: inherit; color: #757575;\">(52)</span></span>"
        },
        "disclaimerBadge": null,
        "fareBadge": null,
        "fareInfo": {
            "serviceFee": 30,
            "serviceFeeCents": 3000
        },
        "promotion": null,
        "shouldIndex": true,
        "heroImageUrls": [
            {
                "url": "https://d1ralsognjng37.cloudfront.net/8d72761b-aca5-417a-aad5-98217a243b4c.jpeg",
                "width": 240
            },
            {
                "url": "https://d1ralsognjng37.cloudfront.net/81798bf9-a866-4bde-b428-c0f8720a0129.jpeg",
                "width": 550
            },
            {
                "url": "https://d1ralsognjng37.cloudfront.net/55939bca-a106-4c64-a59d-37a460bbf6cc.jpeg",
                "width": 640
            },
            {
                "url": "https://d1ralsognjng37.cloudfront.net/ce483faa-5c09-486d-8bd3-86ba86e81896.jpeg",
                "width": 750
            },
            {
                "url": "https://d1ralsognjng37.cloudfront.net/ec33dfc7-4c13-499c-9d05-1e88b86f6485.jpeg",
                "width": 1080
            },
            {
                "url": "https://d1ralsognjng37.cloudfront.net/ffea7073-2e61-4287-8723-2d616e4d3f73.jpeg",
                "width": 2880
            }
        ],
        "isOpen": true,
        "currencyCode": "UAH",
        "closedMessage": "Currently unavailable",
        "location": {
            "address": "Peremohy Ave, 26, Kyiv, 02000",
            "streetAddress": "Peremohy Ave, 26",
            "city": "Kyiv",
            "country": "UA",
            "postalCode": "02000",
            "region": "",
            "latitude": 50.4514016,
            "longitude": 30.468116
        },
        "isDeliveryThirdParty": false,
        "hours": [
            {
                "dayRange": "Every Day",
                "sectionHours": [
                    {
                        "startTime": 600,
                        "endTime": 1290,
                        "sectionTitle": ""
                    }
                ]
            }
        ],
        "disableOrderInstruction": false,
        "disableCheckoutInstruction": false,
        "nuggets": [],
        "isWithinDeliveryRange": false,
        "slug": "pizza-king-просп-перемоги",
        "citySlug": "kyiv",
        "phoneNumber": "+380443334218",
        "metaJson": "{\"@context\":\"http:\\u002F\\u002Fschema.org\",\"@type\":\"Restaurant\",\"@id\":\"https:\\u002F\\u002Fwww.ubereats.com\\u002Fen-UA\\u002Fkyiv\\u002Ffood-delivery\\u002Fpizza-king-%D0%BF%D1%80%D0%BE%D1%81%D0%BF-%D0%BF%D0%B5%D1%80%D0%B5%D0%BC%D0%BE%D0%B3%D0%B8\\u002FUSu0VK8rSHyuEomVRRk0GQ\\u002F\",\"name\":\"Pizza King (просп. Перемоги)\",\"priceRange\":\"₴₴\",\"potentialAction\":{\"@type\":\"OrderAction\",\"target\":{\"@type\":\"EntryPoint\",\"urlTemplate\":\"https:\\u002F\\u002Fwww.ubereats.com\\u002Fen-UA\\u002Fkyiv\\u002Ffood-delivery\\u002Fpizza-king-%D0%BF%D1%80%D0%BE%D1%81%D0%BF-%D0%BF%D0%B5%D1%80%D0%B5%D0%BC%D0%BE%D0%B3%D0%B8\\u002FUSu0VK8rSHyuEomVRRk0GQ\\u002F?utm_campaign=order-action&utm_medium=organic\",\"inLanguage\":\"English\",\"actionPlatform\":[\"http:\\u002F\\u002Fschema.org\\u002FDesktopWebPlatform\",\"http:\\u002F\\u002Fschema.org\\u002FMobileWebPlatform\"]},\"deliveryMethod\":[\"http:\\u002F\\u002Fpurl.org\\u002Fgoodrelations\\u002Fv1#DeliveryModeOwnFleet\"]},\"address\":{\"@type\":\"PostalAddress\",\"addressLocality\":\"Kyiv\",\"addressRegion\":\"\",\"postalCode\":\"02000\",\"addressCountry\":\"UA\",\"streetAddress\":\"Peremohy Ave, 26\"},\"geo\":{\"@type\":\"GeoCoordinates\",\"latitude\":50.4514016,\"longitude\":30.468116}}",
        "promoTrackings": [],
        "suggestedPromotion": {
            "text": "",
            "promotionUuid": ""
        },
        "supportedDiningModes": [
            {
                "mode": "DELIVERY",
                "title": "Delivery",
                "isSelected": true,
                "isAvailable": true
            }
        ],
        "isPreview": false,
        "pinnedInfo": null
    }
}